<current_version>
<appversion>20210709-001</appversion>
<dbversion>20210709-001</dbversion>
<advanced_search>20210709-001</advanced_search>
<api>20210709-001</api>
<assessments>20210709-001</assessments>
<authentication>20210709-001</authentication>
<complianceforgescf>20210709-001</complianceforgescf>
<customization>20210709-001</customization>
<encryption>20210709-001</encryption>
<importexport>20210709-001</importexport>
<incident_management>20210709-001</incident_management>
<jira>20210709-001</jira>
<notification>20210709-001</notification>
<organizational_hierarchy>20210709-001</organizational_hierarchy>
<separation>20210709-001</separation>
<ucf>20210709-001</ucf>
<upgrade>20210709-001</upgrade>
</current_version>
